ava_llm/__init__.py
ava_llm/conversations/__init__.py
ava_llm/conversations/buffer.py
ava_llm/conversations/chat_history.py
ava_llm/conversations/chat_memory.py
ava_llm/conversations/memory.py
ava_llm/conversations/messages/__init__.py
ava_llm/conversations/messages/ai.py
ava_llm/conversations/messages/base.py
ava_llm/conversations/messages/human.py
ava_llm/handlers/__init__.py
ava_llm/handlers/meta.py
ava_llm/handlers/openai.py
ava_llm/language_models/__init__.py
ava_llm/language_models/llm.py
ava_llm/prompts/__init__.py
ava_llm/prompts/base.py
ava_llm/prompts/template.py
ava_llm/utils/__init__.py
ava_llm/utils/utils.py
ava_llm-0.0.32.dist-info/LICENSE
ava_llm-0.0.32.dist-info/METADATA
ava_llm-0.0.32.dist-info/WHEEL
ava_llm-0.0.32.dist-info/top_level.txt
ava_llm-0.0.32.dist-info/RECORD
