Metadata-Version: 2.1
Name: ava-llm
Version: 0.0.32
Summary: A simple llm package.
Home-page: UNKNOWN
License: UNKNOWN
Keywords: python
Platform: UNKNOWN
Classifier: Programming Language :: Python :: 3
Classifier: License :: OSI Approved :: MIT License
Classifier: Operating System :: OS Independent
License-File: LICENSE
Requires-Dist: groq
Requires-Dist: openai
Requires-Dist: python-dotenv
